[
  {
    "time": "2026-06-04 10:32",
    "downloads": 66868
  },
  {
    "time": "2026-06-04 14:28",
    "downloads": 66980
  },
  {
    "time": "2026-06-04 18:06",
    "downloads": 67102
  },
  {
    "time": "2026-06-04 21:21",
    "downloads": 67208
  },
  {
    "time": "2026-06-04 22:59",
    "downloads": 67236
  },
  {
    "time": "2026-06-05 02:03",
    "downloads": 67292
  },
  {
    "time": "2026-06-05 07:57",
    "downloads": 67422
  },
  {
    "time": "2026-06-05 11:23",
    "downloads": 67509
  },
  {
    "time": "2026-06-05 14:18",
    "downloads": 67567
  },
  {
    "time": "2026-06-05 17:44",
    "downloads": 67701
  },
  {
    "time": "2026-06-05 19:27",
    "downloads": 67768
  }
]
